rasc/__init__.py
rasc/cli.py
rasc/storage.py
rasc-0.1.1.dist-info/entry_points.txt
rasc-0.1.1.dist-info/WHEEL
rasc-0.1.1.dist-info/METADATA
rasc-0.1.1.dist-info/RECORD
